setup.py
django_static_management/__init__.py
django_static_management/lib.py
django_static_management/models.py
django_static_management/versioners.py
django_static_management/writers.py
django_static_management.egg-info/PKG-INFO
django_static_management.egg-info/SOURCES.txt
django_static_management.egg-info/dependency_links.txt
django_static_management.egg-info/not-zip-safe
django_static_management.egg-info/requires.txt
django_static_management.egg-info/top_level.txt