Metadata-Version: 1.0
Name: django-static-management
Version: 1.3.0
Summary: An easy way of managing static (CSS and JS) assets in Django projects, including build scripts.
Home-page: https://github.com/bradleywright/django-static-management
Author: Bradley Wright
Author-email: brad@intranation.com
License: BSD
Platform: any
Classifier: Environment :: Web Environment
Classifier: Intended Audience :: Developers
Classifier: License :: OSI Approved :: BSD License
Classifier: Operating System :: OS Independent
Classifier: Programming Language :: Python
Classifier: Topic :: Internet :: WWW/HTTP :: Dynamic Content
Classifier: Topic :: Software Development :: Libraries :: Python Modules
